pycuteweb/__init__.py
pycuteweb/pycuteweb.py
pycuteweb/splash.py
pycuteweb/window.py
pycuteweb-0.1.1.dist-info/LICENSE
pycuteweb-0.1.1.dist-info/METADATA
pycuteweb-0.1.1.dist-info/WHEEL
pycuteweb-0.1.1.dist-info/top_level.txt
pycuteweb-0.1.1.dist-info/RECORD
