Metadata-Version: 2.1
Name: pycuteweb
Version: 0.1.1
Summary: Package which aims to display webapps or websites on a desktop window
Home-page: https://github.com/matteomeneghetti/pycuteweb
Author: Matteo Meneghetti
Author-email: matteo@meneghetti.dev
License: UNKNOWN
Platform: UNKNOWN
Classifier: Development Status :: 3 - Alpha
Classifier: Intended Audience :: Developers
Classifier: Topic :: Software Development :: Build Tools
Classifier: License :: OSI Approved :: MIT License
Classifier: Programming Language :: Python :: 3
Requires-Python: >=3.6
Requires-Dist: pyside2
